Metadata-Version: 2.1
Name: BibFilmes
Version: 1.0.4
Author: Luiz Felipe
Author-email: luiz.nogueira@ufpi.edu.br
License: MIT License
Keywords: BibFilmes
License-File: LICENSE
Requires-Dist: requests
Requires-Dist: pandas
Requires-Dist: pyarrow
